rpi_dots/__init__.py
rpi_dots/vec2d.py
rpi_dots/plane.py
rpi_dots-0.2.3.dist-info/WHEEL
rpi_dots-0.2.3.dist-info/RECORD
rpi_dots-0.2.3.dist-info/top_level.txt
rpi_dots-0.2.3.dist-info/metadata.json
rpi_dots-0.2.3.dist-info/METADATA
rpi_dots-0.2.3.dist-info/DESCRIPTION.rst
rpi_dots-0.2.3.data/scripts/rpi_dots
