Metadata-Version: 2.0
Name: rpi-dots
Version: 0.2.3
Summary: Software for the DOTS board for the Raspberry Pi
Home-page: https://github.com/raspberrypilearning/dots
Author: Ben Nuttall
Author-email: ben@raspberrypi.org
License: BSD
Keywords: raspberrypi,dots,dots board,connect the dots,bare conductive,conductive paint
Platform: UNKNOWN
Classifier: Programming Language :: Python :: 2
Classifier: Programming Language :: Python :: 3
Classifier: Topic :: Games/Entertainment :: Puzzle Games
Classifier: License :: OSI Approved :: BSD License
Classifier: Development Status :: 4 - Beta
